fastarray/__init__.py
fastarray/backend.py
fastarray/compression.py
fastarray/fastarray.py
fastarray/index.py
fastarray/jax_fastarray.py
fastarray/jax_integration.py
fastarray/jax_training_integration.py
fastarray/linalg.py
fastarray/memory.py
fastarray/numpy_api.py
fastarray/random.py
fastml_unified-2.0.0.dist-info/METADATA
fastml_unified-2.0.0.dist-info/WHEEL
fastml_unified-2.0.0.dist-info/top_level.txt
fastml_unified-2.0.0.dist-info/RECORD
